mycalc/calculator.py
lhw0841-0.0.1.dist-info/METADATA
lhw0841-0.0.1.dist-info/WHEEL
lhw0841-0.0.1.dist-info/top_level.txt
lhw0841-0.0.1.dist-info/RECORD
