Metadata-Version: 2.1
Name: lhw0841
Version: 0.0.1
Summary: calculator.py
Author: sj chun
License: UNKNOWN
Platform: UNKNOWN
Classifier: Programming Language :: Python :: 3
